[
    {
      "veiculo": "Carro",
      "bind": "1"
    },
    {
      "veiculo": "Moto",
      "bind": "2"
    },
    {
      "veiculo": "VUC",
      "bind": "3"
    },
    {
      "veiculo": "Caminhao 2",
      "bind": "4"
    },
    {
      "veiculo": "Caminhao 3",
      "bind": "5"
    },
    {
      "veiculo": "Caminhao 4",
      "bind": "6"
    },
    {
      "veiculo": "Carreta 3",
      "bind": "q"
    },
    {
      "veiculo": "Carreta 4",
      "bind": "7"
    },
    {
      "veiculo": "Carreta 5",
      "bind": "x"
    },
    {
      "veiculo": "Carreta 6",
      "bind": "u"
    },
    {
      "veiculo": "Carreta 7",
      "bind": "h"
    },
    {
      "veiculo": "Carreta 9",
      "bind": "s"
    },
    {
      "veiculo": "Carreta 10+",
      "bind": "w"
    },
    {
      "veiculo": "Onibus 2",
      "bind": "i"
    },
    {
      "veiculo": "Onibus 3",
      "bind": "f"
    }
  ]